Sliding Accumulator/adder.v
module adder (
    input        clk,
    input  [5:0] din,
    input        en,
    input        rst_n,
    output [7:0] dout
);

  reg [7:0] p;
  reg [7:0] p_t;
  reg [7:0] dout_t;
  reg [7:0] q_t1;
  reg [7:0] q_t2;
  reg [7:0] q_t3;
  //reg [7:0] q_t4;
  reg [2:0] cnt_1;
  reg [2:0] cnt_2;
  reg       ce;
  reg       capture_t;
  reg       capture;

  assign dout = dout_t;

  always @(*) begin
    if (cnt_2 != 'd0) begin
      ce = 1;
    end else ce = 0;
  end
  always @(*) begin
    if (cnt_2 == 'd3) begin
        capture_t = 1;
    end else capture_t = 0;
  end
  always @(posedge clk ) begin
    capture <= capture_t;
  end



  always @(posedge clk or negedge rst_n) begin
    if (!rst_n) begin
      cnt_1 <= 'd0;
    end else if (en) begin
      if (cnt_1 == 'd4) begin
        cnt_1 <= 'd1;
      end else begin
        cnt_1 <= cnt_1 + 1;
      end
    end else cnt_1 <= 'd0;
  end
  always @(posedge clk or negedge rst_n) begin
    if (!rst_n) begin
      cnt_2 <= 'd0;
    end else if (en) begin
      if (cnt_1 == 'd4) begin
        cnt_2 <= cnt_2 + 1;
      end else if (cnt_2 == 'd4) begin
        cnt_2 <= 'd0;
      end else begin
        cnt_2 <= cnt_2;
      end
    end else begin
      cnt_2 <= 'd0;
    end
  end


  always @(posedge clk or negedge rst_n) begin
    if (!rst_n) begin
      p    <= 'd0;
      q_t1 <= 'd0;
      q_t2 <= 'd0;
      q_t3 <= 'd0;
      //q_t4 <= 'd0;
    end else if (en) begin
      p    <= p_t;
      q_t1 <= p;
      q_t2 <= q_t1;
      q_t3 <= q_t2;
      //q_t4 <= q_t3;
    end else begin
      p    <= p;
      q_t1 <= q_t1;
      q_t2 <= q_t2;
      q_t3 <= q_t3;
    end
  end
  always @(*) begin
    if (ce) begin
      p_t = din + q_t3;
    end else p_t = {2'b0, din};
  end
  always @(posedge clk or negedge rst_n) begin
    if (!rst_n) begin
        dout_t <= 'd0;
    end else if (capture) begin
        dout_t <= p;
    end else begin
        dout_t <= 'd0;
    end
  end


endmodule

adder/tb_adder.v
module adder_tb;

  // Parameters

  // Ports
  reg clk = 0;
  reg [5:0] din;
  reg en = 0;
  reg rst_n = 0;
  wire [7:0] dout;
/*
md build
iverilog -o ./build/test.out  tb_test.v test.v
vvp -n ./build/test.out
gtkwave ./build/wave.vcd
*/

  adder 
  adder_dut (
    .clk (clk ),
    .din (din ),
    .en (en ),
    .rst_n (rst_n ),
    .dout  ( dout)
  );

  initial begin
    $dumpfile("./build/wave.vcd");
    $dumpvars(0,adder_tb);
    #10000 $finish;
  end
  initial begin
    reset_mod();
    en = 1;
    #5 din <= 'd0;
    #10 din <= 'd1;
    #10 din <= 'd2;
    #10 din <= 'd3;
    #10 din <= 'd4;
    #10 din <= 'd5;
    #10 din <= 'd6;
    #10 din <= 'd7;
    #10 din <= 'd8;
    #10 din <= 'd9;
    #10 din <= 'd10;
    #10 din <= 'd11;
    #10 din <= 'd12;
    #10 din <= 'd13;
    #10 din <= 'd14;
    #10 din <= 'd15;
    #20 en = 0;

  end

  always
    #5  clk = ! clk ;

    task reset_mod ();
        begin
            rst_n = 1;
            #50 rst_n = 0;
            #50 rst_n = 1;
            #20;
        end
    endtask
endmodule

Sliding Accumulator/project_1/project_1.sim/sim_1/behav/xsim/dump.vcd
$date
   Tue Jun 13 15:42:00 2023
$end
$version
  2018.3
$end
$timescale
  1ps
$end
$scope module adder_tb $end
$var reg 1 ! clk $end
$var reg 6 " din [5:0] $end
$var reg 1 # en $end
$var reg 1 $ rst_n $end
$var wire 8 % dout [7:0] $end
$scope module adder_dut $end
$var wire 1 & clk $end
$var wire 6 ' din [5:0] $end
$var wire 1 ( en $end
$var wire 1 ) rst_n $end
$var wire 8 % dout [7:0] $end
$var reg 8 * p [7:0] $end
$var reg 8 + p_t [7:0] $end
$var reg 8 , dout_t [7:0] $end
$var reg 8 - q_t1 [7:0] $end
$var reg 8 . q_t2 [7:0] $end
$var reg 8 / q_t3 [7:0] $end
$var reg 3 0 cnt_1 [2:0] $end
$var reg 3 1 cnt_2 [2:0] $end
$var reg 1 2 ce $end
$var reg 1 3 capture_t $end
$var reg 1 4 capture $end
$upscope $end
$scope task reset_mod $end
$upscope $end
$upscope $end
$enddefinitions $end
#0
$dumpvars
0!
bx "
0#
1$
b0 %
0&
bx '
0(
1)
bx *
b0xxxxxx +
b0 ,
bx -
bx .
bx /
b0 0
b0 1
02
03
x4
$end
#5000
1!
1&
04
#10000
0!
0&
#15000
1!
1&
#20000
0!
0&
#25000
1!
1&
#30000
0!
0&
#35000
1!
1&
#40000
0!
0&
#45000
1!
1&
#50000
0!
0$
0&
0)
b0 *
b0 -
b0 .
b0 /
#55000
1!
1&
#60000
0!
0&
#65000
1!
1&
#70000
0!
0&
#75000
1!
1&
#80000
0!
0&
#85000
1!
1&
#90000
0!
0&
#95000
1!
1&
#100000
0!
1$
0&
1)
#105000
1!
1&
#110000
0!
0&
#115000
1!
1&
#120000
0!
1#
0&
1(
#125000
1!
b0 "
1&
b0 '
b0xxxxxx *
b0 +
b1 0
#130000
0!
0&
#135000
1!
b1 "
1&
b1 '
b0 *
b1 +
b0xxxxxx -
b10 0
#140000
0!
0&
#145000
1!
b10 "
1&
b10 '
b1 *
b10 +
b0 -
b0xxxxxx .
b11 0
#150000
0!
0&
#155000
1!
b11 "
1&
b11 '
b10 *
b11 +
b1 -
b0 .
b0xxxxxx /
b100 0
#160000
0!
0&
#165000
1!
b100 "
1&
b100 '
b11 *
b100 +
b10 -
b1 .
b0 /
b1 0
b1 1
12
#170000
0!
0&
#175000
1!
b101 "
1&
b101 '
b100 *
b110 +
b11 -
b10 .
b1 /
b10 0
#180000
0!
0&
#185000
1!
b110 "
1&
b110 '
b110 *
b1000 +
b100 -
b11 .
b10 /
b11 0
#190000
0!
0&
#195000
1!
b111 "
1&
b111 '
b1000 *
b1010 +
b110 -
b100 .
b11 /
b100 0
#200000
0!
0&
#205000
1!
b1000 "
1&
b1000 '
b1010 *
b1100 +
b1000 -
b110 .
b100 /
b1 0
b10 1
#210000
0!
0&
#215000
1!
b1001 "
1&
b1001 '
b1100 *
b1111 +
b1010 -
b1000 .
b110 /
b10 0
#220000
0!
0&
#225000
1!
b1010 "
1&
b1010 '
b1111 *
b10010 +
b1100 -
b1010 .
b1000 /
b11 0
#230000
0!
0&
#235000
1!
b1011 "
1&
b1011 '
b10010 *
b10101 +
b1111 -
b1100 .
b1010 /
b100 0
#240000
0!
0&
#245000
1!
b1100 "
1&
b1100 '
b10101 *
b11000 +
b10010 -
b1111 .
b1100 /
b1 0
b11 1
13
#250000
0!
0&
#255000
1!
b1101 "
1&
b1101 '
b11000 *
b11100 +
b10101 -
b10010 .
b1111 /
b10 0
14
#260000
0!
0&
#265000
1!
b1110 "
b11000 %
1&
b1110 '
b11100 *
b100000 +
b11000 ,
b11000 -
b10101 .
b10010 /
b11 0
#270000
0!
0&
#275000
1!
b1111 "
b11100 %
1&
b1111 '
b100000 *
b100100 +
b11100 ,
b11100 -
b11000 .
b10101 /
b100 0
#280000
0!
0&
#285000
1!
b100000 %
1&
b100100 *
b100111 +
b100000 ,
b100000 -
b11100 .
b11000 /
b1 0
b100 1
03
#290000
0!
0&
#295000
1!
0#
b100100 %
1&
0(
b1111 +
b100100 ,
b0 0
b0 1
02
04
#300000
0!
0&
#305000
1!
b0 %
1&
b0 ,
