Sliding Accumulator/adder.v
module adder (
    input        clk,
    input  [5:0] din,
    input        en,
    input        rst_n,
    output [7:0] dout
);

  reg [7:0] p;
  reg [7:0] p_t;
  reg [7:0] dout_t;
  reg [7:0] q_t1;
  reg [7:0] q_t2;
  reg [7:0] q_t3;
  //reg [7:0] q_t4;
  reg [2:0] cnt_1;
  reg [2:0] cnt_2;
  reg       ce;
  reg       capture_t;
  reg       capture;

  assign dout = dout_t;

  always @(*) begin
    if (cnt_2 != 'd0) begin
      ce = 1;
    end else ce = 0;
  end
  always @(*) begin
    if (cnt_2 == 'd3) begin
        capture_t = 1;
    end else capture_t = 0;
  end
  always @(posedge clk ) begin
    capture <= capture_t;
  end



  always @(posedge clk or negedge rst_n) begin
    if (!rst_n) begin
      cnt_1 <= 'd0;
    end else if (en) begin
      if (cnt_1 == 'd4) begin
        cnt_1 <= 'd1;
      end else begin
        cnt_1 <= cnt_1 + 1;
      end
    end else cnt_1 <= 'd0;
  end
  always @(posedge clk or negedge rst_n) begin
    if (!rst_n) begin
      cnt_2 <= 'd0;
    end else if (en) begin
      if (cnt_1 == 'd4) begin
        cnt_2 <= cnt_2 + 1;
      end else if (cnt_2 == 'd4) begin
        cnt_2 <= 'd0;
      end else begin
        cnt_2 <= cnt_2;
      end
    end else begin
      cnt_2 <= 'd0;
    end
  end


  always @(posedge clk or negedge rst_n) begin
    if (!rst_n) begin
      p    <= 'd0;
      q_t1 <= 'd0;
      q_t2 <= 'd0;
      q_t3 <= 'd0;
      //q_t4 <= 'd0;
    end else if (en) begin
      p    <= p_t;
      q_t1 <= p;
      q_t2 <= q_t1;
      q_t3 <= q_t2;
      //q_t4 <= q_t3;
    end else begin
      p    <= p;
      q_t1 <= q_t1;
      q_t2 <= q_t2;
      q_t3 <= q_t3;
    end
  end
  always @(*) begin
    if (ce) begin
      p_t = din + q_t3;
    end else p_t = {2'b0, din};
  end
  always @(posedge clk or negedge rst_n) begin
    if (!rst_n) begin
        dout_t <= 'd0;
    end else if (capture) begin
        dout_t <= p;
    end else begin
        dout_t <= 'd0;
    end
  end


endmodule

adder/tb_adder.v
module adder_tb;

  // Parameters

  // Ports
  reg clk = 0;
  reg [5:0] din;
  reg en = 0;
  reg rst_n = 0;
  wire [7:0] dout;
/*
md build
iverilog -o ./build/test.out  tb_test.v test.v
vvp -n ./build/test.out
gtkwave ./build/wave.vcd
*/

  adder 
  adder_dut (
    .clk (clk ),
    .din (din ),
    .en (en ),
    .rst_n (rst_n ),
    .dout  ( dout)
  );

  initial begin
    $dumpfile("./build/wave.vcd");
    $dumpvars(0,adder_tb);
    #10000 $finish;
  end
  initial begin
    reset_mod();
    en = 1;
    #5 din <= 'd0;
    #10 din <= 'd1;
    #10 din <= 'd2;
    #10 din <= 'd3;
    #10 din <= 'd4;
    #10 din <= 'd5;
    #10 din <= 'd6;
    #10 din <= 'd7;
    #10 din <= 'd8;
    #10 din <= 'd9;
    #10 din <= 'd10;
    #10 din <= 'd11;
    #10 din <= 'd12;
    #10 din <= 'd13;
    #10 din <= 'd14;
    #10 din <= 'd15;
    #20 en = 0;

  end

  always
    #5  clk = ! clk ;

    task reset_mod ();
        begin
            rst_n = 1;
            #50 rst_n = 0;
            #50 rst_n = 1;
            #20;
        end
    endtask
endmodule

adder/build/wave.vcd
$date
	Tue Jun 13 15:48:18 2023
$end
$version
	Icarus Verilog
$end
$timescale
	1s
$end
$scope module adder_tb $end
$var wire 8 ! dout [7:0] $end
$var reg 1 " clk $end
$var reg 6 # din [5:0] $end
$var reg 1 $ en $end
$var reg 1 % rst_n $end
$scope module adder_dut $end
$var wire 1 " clk $end
$var wire 6 & din [5:0] $end
$var wire 8 ' dout [7:0] $end
$var wire 1 $ en $end
$var wire 1 % rst_n $end
$var reg 1 ( capture $end
$var reg 1 ) capture_t $end
$var reg 1 * ce $end
$var reg 3 + cnt_1 [2:0] $end
$var reg 3 , cnt_2 [2:0] $end
$var reg 8 - dout_t [7:0] $end
$var reg 8 . p [7:0] $end
$var reg 8 / p_t [7:0] $end
$var reg 8 0 q_t1 [7:0] $end
$var reg 8 1 q_t2 [7:0] $end
$var reg 8 2 q_t3 [7:0] $end
$upscope $end
$scope task reset_mod $end
$upscope $end
$upscope $end
$enddefinitions $end
$comment Show the parameter values. $end
$dumpall
$end
#0
$dumpvars
bx 2
bx 1
bx 0
b0xxxxxx /
bx .
b0 -
b0 ,
b0 +
0*
0)
x(
b0 '
bx &
1%
0$
bx #
0"
b0 !
$end
#5
0(
1"
#10
0"
#15
1"
#20
0"
#25
1"
#30
0"
#35
1"
#40
0"
#45
1"
#50
b0 2
b0 1
b0 0
b0 .
0"
0%
#55
1"
#60
0"
#65
1"
#70
0"
#75
1"
#80
0"
#85
1"
#90
0"
#95
1"
#100
0"
1%
#105
1"
#110
0"
#115
1"
#120
0"
1$
#125
b0 /
b1 +
b0xxxxxx .
b0 #
b0 &
1"
#130
0"
#135
b1 /
b0xxxxxx 0
b0 .
b10 +
b1 #
b1 &
1"
#140
0"
#145
b10 /
b11 +
b0xxxxxx 1
b0 0
b1 .
b10 #
b10 &
1"
#150
0"
#155
b11 /
b0xxxxxx 2
b0 1
b1 0
b10 .
b100 +
b11 #
b11 &
1"
#160
0"
#165
1*
b100 /
b1 +
b1 ,
b0 2
b1 1
b10 0
b11 .
b100 #
b100 &
1"
#170
0"
#175
b110 /
b1 2
b10 1
b11 0
b100 .
b10 +
b101 #
b101 &
1"
#180
0"
#185
b1000 /
b11 +
b10 2
b11 1
b100 0
b110 .
b110 #
b110 &
1"
#190
0"
#195
b1010 /
b11 2
b100 1
b110 0
b1000 .
b100 +
b111 #
b111 &
1"
#200
0"
#205
b1100 /
b1 +
b10 ,
b100 2
b110 1
b1000 0
b1010 .
b1000 #
b1000 &
1"
#210
0"
#215
b1111 /
b110 2
b1000 1
b1010 0
b1100 .
b10 +
b1001 #
b1001 &
1"
#220
0"
#225
b10010 /
b11 +
b1000 2
b1010 1
b1100 0
b1111 .
b1010 #
b1010 &
1"
#230
0"
#235
b10101 /
b1010 2
b1100 1
b1111 0
b10010 .
b100 +
b1011 #
b1011 &
1"
#240
0"
#245
1)
b11000 /
b1 +
b11 ,
b1100 2
b1111 1
b10010 0
b10101 .
b1100 #
b1100 &
1"
#250
0"
#255
b11100 /
b1111 2
b10010 1
b10101 0
b11000 .
b10 +
1(
b1101 #
b1101 &
1"
#260
0"
#265
b100000 /
b11 +
b10010 2
b10101 1
b11000 0
b11100 .
b11000 !
b11000 '
b11000 -
b1110 #
b1110 &
1"
#270
0"
#275
b100100 /
b11100 !
b11100 '
b11100 -
b10101 2
b11000 1
b11100 0
b100000 .
b100 +
b1111 #
b1111 &
1"
#280
0"
#285
0)
b100111 /
b1 +
b100 ,
b11000 2
b11100 1
b100000 0
b100100 .
b100000 !
b100000 '
b100000 -
1"
#290
0"
#295
b1111 /
0*
b100100 !
b100100 '
b100100 -
b0 ,
b0 +
0(
1"
0$
#300
0"
#305
b0 !
b0 '
b0 -
1"
